pymontecarlo_penepma/__init__.py
pymontecarlo_penepma/_version.py
pymontecarlo_penepma/conftest.py
pymontecarlo_penepma/expander.py
pymontecarlo_penepma/exporter.py
pymontecarlo_penepma/importer.py
pymontecarlo_penepma/interactionforcings.py
pymontecarlo_penepma/program.py
pymontecarlo_penepma/program_gui.py
pymontecarlo_penepma/referenceline.py
pymontecarlo_penepma/simulationparameters.py
pymontecarlo_penepma/test_exporter.py
pymontecarlo_penepma/test_importer.py
pymontecarlo_penepma/test_interactionforcings.py
pymontecarlo_penepma/test_program.py
pymontecarlo_penepma/test_referenceline.py
pymontecarlo_penepma/test_simulationparameters.py
pymontecarlo_penepma/test_worker.py
pymontecarlo_penepma/worker.py
pymontecarlo_penepma/penepma/bin_linux/convolg
pymontecarlo_penepma/penepma/bin_linux/material
pymontecarlo_penepma/penepma/bin_linux/penepma
pymontecarlo_penepma/penepma/bin_win32/convolg.exe
pymontecarlo_penepma/penepma/bin_win32/material.exe
pymontecarlo_penepma/penepma/bin_win32/penepma.exe
pymontecarlo_penepma/penepma/pendbase/pe-material.dat
pymontecarlo_penepma/penepma/pendbase/penepma.dat
pymontecarlo_penepma/penepma/pendbase/pdfiles/eeldx001.p08
pymontecarlo_penepma/penepma/pendbase/pdfiles/eeldx002.p08
pymontecarlo_penepma/penepma/pendbase/pdfiles/eeldx003.p08
pymontecarlo_penepma/penepma/pendbase/pdfiles/eeldx004.p08
pymontecarlo_penepma/penepma/pendbase/pdfiles/eeldx005.p08
pymontecarlo_penepma/penepma/pendbase/pdfiles/eeldx006.p08
pymontecarlo_penepma/penepma/pendbase/pdfiles/eeldx007.p08
pymontecarlo_penepma/penepma/pendbase/pdfiles/eeldx008.p08
pymontecarlo_penepma/penepma/pendbase/pdfiles/eeldx009.p08
pymontecarlo_penepma/penepma/pendbase/pdfiles/eeldx010.p08
pymontecarlo_penepma/penepma/pendbase/pdfiles/eeldx011.p08
pymontecarlo_penepma/penepma/pendbase/pdfiles/eeldx012.p08
pymontecarlo_penepma/penepma/pendbase/pdfiles/eeldx013.p08
pymontecarlo_penepma/penepma/pendbase/pdfiles/eeldx014.p08
pymontecarlo_penepma/penepma/pendbase/pdfiles/eeldx015.p08
pyMonteCarlo_PENEPMA-1.0.0.dist-info/LICENSE
pyMonteCarlo_PENEPMA-1.0.0.dist-info/METADATA
pyMonteCarlo_PENEPMA-1.0.0.dist-info/WHEEL
pyMonteCarlo_PENEPMA-1.0.0.dist-info/top_level.txt
pyMonteCarlo_PENEPMA-1.0.0.dist-info/RECORD
