Metadata-Version: 2.1
Name: pyMonteCarlo-PENEPMA
Version: 1.0.0
Summary: Interface of Monte Carlo simulation program PENEPMA with pyMonteCarlo
Home-page: https://github.com/pymontecarlo
Author: Hendrix Demers and Philippe T. Pinard
Author-email: philippe.pinard@gmail.com
License: Apache License version 2.0
Platform: UNKNOWN
Classifier: Development Status :: 4 - Beta
Classifier: Intended Audience :: End Users/Desktop
Classifier: License :: OSI Approved :: GNU General Public License (GPL)
Classifier: Natural Language :: English
Classifier: Programming Language :: Python
Classifier: Operating System :: OS Independent
Classifier: Topic :: Scientific/Engineering
Classifier: Topic :: Scientific/Engineering :: Physics
License-File: LICENSE
Requires-Dist: h5py
Requires-Dist: numpy
Requires-Dist: pymontecarlo
Requires-Dist: pypenelopetools
Requires-Dist: pyxray
